LabTest/2017-18 Waveform Generator/MUX_SMALL.v
module MUX_SMALL(sel, in, out);
    input sel;
    input[1:0] in;
    output out;

    assign out = (~sel & in[0]) | (sel & in[1]);
endmodule

LabTest/2017-18 Waveform Generator/MUX_BIG.v
`include "MUX_SMALL.v"
module MUX_BIG(sel, in, out);
    input[2:0] sel;
    input[7:0] in;
    output out;

    wire[5:0] w;

    MUX_SMALL m0(sel[0], in[1:0], w[0]);
    MUX_SMALL m1(sel[0], in[3:2], w[1]);
    MUX_SMALL m2(sel[0], in[5:4], w[2]);
    MUX_SMALL m3(sel[0], in[7:6], w[3]);

    MUX_SMALL m4(sel[1], w[1:0], w[4]);
    MUX_SMALL m5(sel[1], w[3:2], w[5]);

    MUX_SMALL m6(sel[2], w[5:4], out);
endmodule
/*
module tb_MUX_BIG;
    reg[2:0] sel;
    reg [7:0] in;
    wire out;

    MUX_BIG MB(sel, in, out);

    initial
        begin
          $monitor($time, " Sel = %b, Input = %b, Out = %b", sel, in, out);
          #0 in = 8'b10111000;
          #5 sel = 3'b000;
          #5 sel = 3'b001;
          #5 sel = 3'b010;
          #5 sel = 3'b011;
          #5 sel = 3'b100;
          #5 sel = 3'b101;
          #5 sel = 3'b110;
          #5 sel = 3'b111;
          #5 $finish;
        end
endmodule
*/

LabTest/2017-18 Waveform Generator/TFF.v
`ifndef TFF
`define TFF
module TFF(q, t, clk, reset);
    input t, clk, reset;
    output q;
    reg q;

    always @(reset or posedge clk)
        begin
          if(reset)
            q <= 1'b0;
          else
            begin
              if(t == 1)
                q <= ~q;
              else
                q <= q;
            end
        end
endmodule
/*
module tb_TFF;
  reg t, reset, clk;
  wire q;
  TFF tff(q, t, clk, reset);
  
  initial 
    clk = 1'b0;
    
  always
    #2 clk = ~clk;
  
  initial
    begin
      $monitor($time, " T = %b, Reset = %b, Clock = %b, Q = %b.", t, reset, clk, q);
      #4 t = 1'b0; reset = 1'b0;
      #4 t = 1'b1; reset = 1'b1;
      #4 t = 1'b0; reset = 1'b1;
      #4 t = 1'b1; reset = 1'b1;
      #4 $finish;
    end
endmodule
*/
`endif

LabTest/2017-18 Waveform Generator/COUNTER_3BIT.v
`include "TFF.v"
module COUNTER_3BIT(clear, clock, q);
    input clear, clock;
    output[2:0] q;

    reg [2:0]q;

    initial 
        q = 3'b0;

    wire in1, in3;
    wire [2:0] out;
    assign in1 = 1'b1;
    and( in3, out[1], out[0]);
    
    TFF ff1(out[0], in1, clock, clear);
    TFF ff2(out[1], out[0], clock, clear);
    TFF ff3(out[2], in3, clock, clear);

    always @(posedge clock or clear) 
      begin
        if(clear)
            q <= 3'b0;
        else
            q <= out;
    end
endmodule

LabTest/2017-18 Waveform Generator/COUNTER_4BIT.v
`include "TFF.v"
module COUNTER_4BIT(clear, clock, q);
    input clear, clock;
    output[3:0] q;

    reg [3:0]q;

    initial 
        q = 4'b0;

    wire in1, in3, in4;
    wire [3:0] out;
    assign in1 = 1'b1;
    and( in3, out[1], out[0]);
    and( in4, out[2], in3);
    
    TFF ff1(out[0], in1, clock, clear);
    TFF ff2(out[1], out[0], clock, clear);
    TFF ff3(out[2], in3, clock, clear);
    TFF ff4(out[3], in4, clock, clear);

    always @(posedge clock or clear) 
      begin
        if(clear)
            q = 4'b0;
        else
            q = out;
    end
endmodule

LabTest/2017-18 Waveform Generator/MEMORY.v
module MEMORY;
    reg[7:0] mem[0:15];

    integer i;

    initial
        begin
          for(i = 0; i < 16; i = i+1)
            begin
              if(i % 2 == 0)
                mem[i] = 8'b11001100;
              else
                mem[i] = 8'b10101010;
            end
        end
endmodule

LabTest/2017-18 Waveform Generator/INTG.v
`include "TFF.v"
`include "MUX_BIG.v"
`include "COUNTER_4BIT.v"
`include "COUNTER_3BIT.v"
`include "MEMORY.v"
`timescale 1ms/1ns

module INTG(clear, clk, wf);
    input clear, clk;
    output wf;

    wire clk_COUNTER4BIT;
    wire[3:0] op_COUNTER4BIT;
    wire[2:0] op_COUNTER3BIT;

    and(clk_COUNTER4BIT, op_COUNTER3BIT[0], op_COUNTER3BIT[1], op_COUNTER3BIT[2]);

    MEMORY MEM();
    COUNTER_4BIT cnt4(clear, clk_COUNTER4BIT, op_COUNTER4BIT);
    COUNTER_3BIT cnt3(clear, clk, op_COUNTER3BIT);
    MUX_BIG mb(op_COUNTER3BIT, MEM.mem[op_COUNTER4BIT], wf);
endmodule

module tb_INTG;
    initial 
        begin
            $dumpfile("tb_INTG.vcd");
            $dumpvars;
        end

    reg clear, clock;
    wire wf;

    INTG intg(clear, clock, wf);

    initial 
        clock = 1'b0;
    always
        #0.5 clock = ~clock;
    
    initial begin
            clear = 1'b1;
        #1  clear = 1'b0;
        #1000 $finish;
    end

    // initial 
    //     $monitor("Main := clock = %b, clear = %b, wf = %b \n Cntr3bit := clock = %b, q = %d \n Cntr4bit := clock = %b, q = %d \n MuxLarge := input = %b, sel = %d, output = %b\n\n",clock, clear, wf, mod.cnt3bit.clock, mod.cnt3bit.q,mod.cnt4bit.clock, mod.cnt4bit.q,mod.mux.inp,mod.mux.sel, mod.mux.outp);
endmodule

LabTest/2017-18 Waveform Generator/tb_INTG.vcd
$date
	Sun Nov  3 23:50:07 2019
$end
$version
	Icarus Verilog
$end
$timescale
	1ns
$end
$scope module tb_INTG $end
$var wire 1 ! wf $end
$var reg 1 " clear $end
$var reg 1 # clock $end
$scope module intg $end
$var wire 1 " clear $end
$var wire 1 # clk $end
$var wire 1 $ clk_COUNTER4BIT $end
$var wire 1 ! wf $end
$var wire 4 % op_COUNTER4BIT [3:0] $end
$var wire 3 & op_COUNTER3BIT [2:0] $end
$scope module MEM $end
$var integer 32 ' i [31:0] $end
$upscope $end
$scope module cnt3 $end
$var wire 1 " clear $end
$var wire 1 # clock $end
$var wire 1 ( in1 $end
$var wire 1 ) in3 $end
$var wire 3 * out [2:0] $end
$var reg 3 + q [2:0] $end
$scope module ff1 $end
$var wire 1 # clk $end
$var wire 1 " reset $end
$var wire 1 ( t $end
$var reg 1 , q $end
$upscope $end
$scope module ff2 $end
$var wire 1 # clk $end
$var wire 1 " reset $end
$var wire 1 - t $end
$var reg 1 . q $end
$upscope $end
$scope module ff3 $end
$var wire 1 # clk $end
$var wire 1 " reset $end
$var wire 1 ) t $end
$var reg 1 / q $end
$upscope $end
$upscope $end
$scope module cnt4 $end
$var wire 1 " clear $end
$var wire 1 $ clock $end
$var wire 1 0 in1 $end
$var wire 1 1 in3 $end
$var wire 1 2 in4 $end
$var wire 4 3 out [3:0] $end
$var reg 4 4 q [3:0] $end
$scope module ff1 $end
$var wire 1 $ clk $end
$var wire 1 " reset $end
$var wire 1 0 t $end
$var reg 1 5 q $end
$upscope $end
$scope module ff2 $end
$var wire 1 $ clk $end
$var wire 1 " reset $end
$var wire 1 6 t $end
$var reg 1 7 q $end
$upscope $end
$scope module ff3 $end
$var wire 1 $ clk $end
$var wire 1 " reset $end
$var wire 1 1 t $end
$var reg 1 8 q $end
$upscope $end
$scope module ff4 $end
$var wire 1 $ clk $end
$var wire 1 " reset $end
$var wire 1 2 t $end
$var reg 1 9 q $end
$upscope $end
$upscope $end
$scope module mb $end
$var wire 8 : in [7:0] $end
$var wire 3 ; sel [2:0] $end
$var wire 6 < w [5:0] $end
$var wire 1 ! out $end
$scope module m0 $end
$var wire 2 = in [1:0] $end
$var wire 1 > out $end
$var wire 1 ? sel $end
$upscope $end
$scope module m1 $end
$var wire 2 @ in [1:0] $end
$var wire 1 A out $end
$var wire 1 B sel $end
$upscope $end
$scope module m2 $end
$var wire 2 C in [1:0] $end
$var wire 1 D out $end
$var wire 1 E sel $end
$upscope $end
$scope module m3 $end
$var wire 2 F in [1:0] $end
$var wire 1 G out $end
$var wire 1 H sel $end
$upscope $end
$scope module m4 $end
$var wire 2 I in [1:0] $end
$var wire 1 J out $end
$var wire 1 K sel $end
$upscope $end
$scope module m5 $end
$var wire 2 L in [1:0] $end
$var wire 1 M out $end
$var wire 1 N sel $end
$upscope $end
$scope module m6 $end
$var wire 2 O in [1:0] $end
$var wire 1 ! out $end
$var wire 1 P sel $end
$upscope $end
$upscope $end
$upscope $end
$upscope $end
$enddefinitions $end
#0
$dumpvars
0P
b0 O
0N
0M
b10 L
0K
0J
b10 I
0H
1G
b11 F
0E
0D
b0 C
0B
1A
b11 @
0?
0>
b0 =
b1010 <
b0 ;
b11001100 :
09
08
07
06
05
b0 4
b0 3
02
01
10
0/
0.
0-
0,
b0 +
b0 *
0)
1(
b10000 '
b0 &
b0 %
0$
0#
1"
0!
$end
#500000
1#
#1000000
1-
16
b1 *
1,
b1 3
15
0#
0"
#1500000
1?
1B
1E
1H
0-
b1 &
b1 +
b1 ;
1.
b10 *
0,
1#
#2000000
0#
#2500000
1!
b10 I
b10 L
b11 O
1A
1G
1J
b111010 <
1M
1)
1-
0?
0B
0E
0H
1K
1N
b11 *
1,
b10 &
b10 +
b10 ;
1#
#3000000
0#
#3500000
0)
1?
1B
1E
1H
0-
b11 &
b11 +
b11 ;
1/
0.
b100 *
0,
1#
#4000000
0#
#4500000
0!
b10 I
b10 L
b0 O
1A
1G
0J
b1010 <
0M
1-
0?
0B
0E
0H
0K
0N
1P
b101 *
1,
b100 &
b100 +
b100 ;
1#
#5000000
0#
#5500000
1?
1B
1E
1H
0-
b101 &
b101 +
b101 ;
1.
b110 *
0,
1#
#6000000
0#
#6500000
1!
b10 I
b10 L
b11 O
1A
1G
1J
b111010 <
1M
1)
1-
0?
0B
0E
0H
1K
1N
b111 *
1,
b110 &
b110 +
b110 ;
1#
#7000000
0#
#7500000
06
05
b10 3
17
b11 I
b11 L
1>
b111111 <
1D
b10 =
b10 @
b10 C
b10 F
b10101010 :
b1 %
b1 4
1$
0)
1?
1B
1E
1H
0-
b111 &
b111 +
b111 ;
0/
0.
b0 *
0,
1#
#8000000
0#
#8500000
b0 I
b0 L
b0 O
0>
0A
0D
0G
0J
b0 <
0M
0!
0$
1-
0?
0B
0E
0H
0K
0N
0P
b1 *
1,
b0 &
b0 +
b0 ;
1#
#9000000
0#
#9500000
1!
b11 O
1J
1M
b11 I
b11 L
1>
1A
1D
b111111 <
1G
1?
1B
1E
1H
0-
b1 &
b1 +
b1 ;
1.
b10 *
0,
1#
#10000000
0#
#10500000
0!
b0 O
0J
0M
b0 I
b0 L
0>
0A
0D
b0 <
0G
1)
1-
0?
0B
0E
0H
1K
1N
b11 *
1,
b10 &
b10 +
b10 ;
1#
#11000000
0#
#11500000
1!
b11 O
1J
1M
b11 I
b11 L
1>
1A
1D
b111111 <
1G
0)
1?
1B
1E
1H
0-
b11 &
b11 +
b11 ;
1/
0.
b100 *
0,
1#
#12000000
0#
#12500000
0!
b0 I
b0 L
b0 O
0>
0A
0D
0G
0J
b0 <
0M
1-
0?
0B
0E
0H
0K
0N
1P
b101 *
1,
b100 &
b100 +
b100 ;
1#
#13000000
0#
#13500000
1!
b11 O
1J
1M
b11 I
b11 L
1>
1A
1D
b111111 <
1G
1?
1B
1E
1H
0-
b101 &
b101 +
b101 ;
1.
b110 *
0,
1#
#14000000
0#
#14500000
0!
b0 O
0J
0M
b0 I
b0 L
0>
0A
0D
b0 <
0G
1)
1-
0?
0B
0E
0H
1K
1N
b111 *
1,
b110 &
b110 +
b110 ;
1#
#15000000
0#
#15500000
11
16
b11 3
15
1!
b11 O
1J
1M
b10 I
b10 L
b0 =
b11 @
b0 C
b11 F
0>
1A
0D
b111010 <
1G
b11001100 :
b10 %
b10 4
1$
0)
1?
1B
1E
1H
0-
b111 &
b111 +
b111 ;
0/
0.
b0 *
0,
1#
#16000000
0#
#16500000
b10 I
b10 L
b0 O
1A
1G
0J
b1010 <
0M
0!
0$
1-
0?
0B
0E
0H
0K
0N
0P
b1 *
1,
b0 &
b0 +
b0 ;
1#
#17000000
0#
#17500000
1?
1B
1E
1H
0-
b1 &
b1 +
b1 ;
1.
b10 *
0,
1#
#18000000
0#
#18500000
1!
b10 I
b10 L
b11 O
1A
1G
1J
b111010 <
1M
1)
1-
0?
0B
0E
0H
1K
1N
b11 *
1,
b10 &
b10 +
b10 ;
1#
#19000000
0#
#19500000
0)
1?
1B
1E
1H
0-
b11 &
b11 +
b11 ;
1/
0.
b100 *
0,
1#
#20000000
0#
#20500000
0!
b10 I
b10 L
b0 O
1A
1G
0J
b1010 <
0M
1-
0?
0B
0E
0H
0K
0N
1P
b101 *
1,
b100 &
b100 +
b100 ;
1#
#21000000
0#
#21500000
1?
1B
1E
1H
0-
b101 &
b101 +
b101 ;
1.
b110 *
0,
1#
#22000000
0#
#22500000
1!
b10 I
b10 L
b11 O
1A
1G
1J
b111010 <
1M
1)
1-
0?
0B
0E
0H
1K
1N
b111 *
1,
b110 &
b110 +
b110 ;
1#
#23000000
0#
#23500000
01
02
06
05
07
b100 3
18
b11 I
b11 L
1>
b111111 <
1D
b10 =
b10 @
b10 C
b10 F
b10101010 :
b11 %
b11 4
1$
0)
1?
1B
1E
1H
0-
b111 &
b111 +
b111 ;
0/
0.
b0 *
0,
1#
#24000000
0#
#24500000
b0 I
b0 L
b0 O
0>
0A
0D
0G
0J
b0 <
0M
0!
0$
1-
0?
0B
0E
0H
0K
0N
0P
b1 *
1,
b0 &
b0 +
b0 ;
1#
#25000000
0#
#25500000
1!
b11 O
1J
1M
b11 I
b11 L
1>
1A
1D
b111111 <
1G
1?
1B
1E
1H
0-
b1 &
b1 +
b1 ;
1.
b10 *
0,
1#
#26000000
0#
#26500000
0!
b0 O
0J
0M
b0 I
b0 L
0>
0A
0D
b0 <
0G
1)
1-
0?
0B
0E
0H
1K
1N
b11 *
1,
b10 &
b10 +
b10 ;
1#
#27000000
0#
#27500000
1!
b11 O
1J
1M
b11 I
b11 L
1>
1A
1D
b111111 <
1G
0)
1?
1B
1E
1H
0-
b11 &
b11 +
b11 ;
1/
0.
b100 *
0,
1#
#28000000
0#
#28500000
0!
b0 I
b0 L
b0 O
0>
0A
0D
0G
0J
b0 <
0M
1-
0?
0B
0E
0H
0K
0N
1P
b101 *
1,
b100 &
b100 +
b100 ;
1#
#29000000
0#
#29500000
1!
b11 O
1J
1M
b11 I
b11 L
1>
1A
1D
b111111 <
1G
1?
1B
1E
1H
0-
b101 &
b101 +
b101 ;
1.
b110 *
0,
1#
#30000000
0#
#30500000
0!
b0 O
0J
0M
b0 I
b0 L
0>
0A
0D
b0 <
0G
1)
1-
0?
0B
0E
0H
1K
1N
b111 *
1,
b110 &
b110 +
b110 ;
1#
#31000000
0#
#31500000
16
b101 3
15
1!
b11 O
1J
1M
b10 I
b10 L
b0 =
b11 @
b0 C
b11 F
0>
1A
0D
b111010 <
1G
b11001100 :
b100 %
b100 4
1$
0)
1?
1B
1E
1H
0-
b111 &
b111 +
b111 ;
0/
0.
b0 *
0,
1#
#32000000
0#
#32500000
b10 I
b10 L
b0 O
1A
1G
0J
b1010 <
0M
0!
0$
1-
0?
0B
0E
0H
0K
0N
0P
b1 *
1,
b0 &
b0 +
b0 ;
1#
#33000000
0#
#33500000
1?
1B
1E
1H
0-
b1 &
b1 +
b1 ;
1.
b10 *
0,
1#
#34000000
0#
#34500000
1!
b10 I
b10 L
b11 O
1A
1G
1J
b111010 <
1M
1)
1-
0?
0B
0E
0H
1K
1N
b11 *
1,
b10 &
b10 +
b10 ;
1#
#35000000
0#
#35500000
0)
1?
1B
1E
1H
0-
b11 &
b11 +
b11 ;
1/
0.
b100 *
0,
1#
#36000000
0#
#36500000
0!
b10 I
b10 L
b0 O
1A
1G
0J
b1010 <
0M
1-
0?
0B
0E
0H
0K
0N
1P
b101 *
1,
b100 &
b100 +
b100 ;
1#
#37000000
0#
#37500000
1?
1B
1E
1H
0-
b101 &
b101 +
b101 ;
1.
b110 *
0,
1#
#38000000
0#
#38500000
1!
b10 I
b10 L
b11 O
1A
1G
1J
b111010 <
1M
1)
1-
0?
0B
0E
0H
1K
1N
b111 *
1,
b110 &
b110 +
b110 ;
1#
#39000000
0#
#39500000
06
05
b110 3
17
b11 I
b11 L
1>
b111111 <
1D
b10 =
b10 @
b10 C
b10 F
b10101010 :
b101 %
b101 4
1$
0)
1?
1B
1E
1H
0-
b111 &
b111 +
b111 ;
0/
0.
b0 *
0,
1#
#40000000
0#
#40500000
b0 I
b0 L
b0 O
0>
0A
0D
0G
0J
b0 <
0M
0!
0$
1-
0?
0B
0E
0H
0K
0N
0P
b1 *
1,
b0 &
b0 +
b0 ;
1#
#41000000
0#
#41500000
1!
b11 O
1J
1M
b11 I
b11 L
1>
1A
1D
b111111 <
1G
1?
1B
1E
1H
0-
b1 &
b1 +
b1 ;
1.
b10 *
0,
1#
#42000000
0#
#42500000
0!
b0 O
0J
0M
b0 I
b0 L
0>
0A
0D
b0 <
0G
1)
1-
0?
0B
0E
0H
1K
1N
b11 *
1,
b10 &
b10 +
b10 ;
1#
#43000000
0#
#43500000
1!
b11 O
1J
1M
b11 I
b11 L
1>
1A
1D
b111111 <
1G
0)
1?
1B
1E
1H
0-
b11 &
b11 +
b11 ;
1/
0.
b100 *
0,
1#
#44000000
0#
#44500000
0!
b0 I
b0 L
b0 O
0>
0A
0D
0G
0J
b0 <
0M
1-
0?
0B
0E
0H
0K
0N
1P
b101 *
1,
b100 &
b100 +
b100 ;
1#
#45000000
0#
#45500000
1!
b11 O
1J
1M
b11 I
b11 L
1>
1A
1D
b111111 <
1G
1?
1B
1E
1H
0-
b101 &
b101 +
b101 ;
1.
b110 *
0,
1#
#46000000
0#
#46500000
0!
b0 O
0J
0M
b0 I
b0 L
0>
0A
0D
b0 <
0G
1)
1-
0?
0B
0E
0H
1K
1N
b111 *
1,
b110 &
b110 +
b110 ;
1#
#47000000
0#
#47500000
12
11
16
b111 3
15
1!
b11 O
1J
1M
b10 I
b10 L
b0 =
b11 @
b0 C
b11 F
0>
1A
0D
b111010 <
1G
b11001100 :
b110 %
b110 4
1$
0)
1?
1B
1E
1H
0-
b111 &
b111 +
b111 ;
0/
0.
b0 *
0,
1#
#48000000
0#
#48500000
b10 I
b10 L
b0 O
1A
1G
0J
b1010 <
0M
0!
0$
1-
0?
0B
0E
0H
0K
0N
0P
b1 *
1,
b0 &
b0 +
b0 ;
1#
#49000000
0#
#49500000
1?
1B
1E
1H
0-
b1 &
b1 +
b1 ;
1.
b10 *
0,
1#
#50000000
0#
#50500000
1!
b10 I
b10 L
b11 O
1A
1G
1J
b111010 <
1M
1)
1-
0?
0B
0E
0H
1K
1N
b11 *
1,
b10 &
b10 +
b10 ;
1#
#51000000
0#
#51500000
0)
1?
1B
1E
1H
0-
b11 &
b11 +
b11 ;
1/
0.
b100 *
0,
1#
#52000000
0#
#52500000
0!
b10 I
b10 L
b0 O
1A
1G
0J
b1010 <
0M
1-
0?
0B
0E
0H
0K
0N
1P
b101 *
1,
b100 &
b100 +
b100 ;
1#
#53000000
0#
#53500000
1?
1B
1E
1H
0-
b101 &
b101 +
b101 ;
1.
b110 *
0,
1#
#54000000
0#
#54500000
1!
b10 I
b10 L
b11 O
1A
1G
1J
b111010 <
1M
1)
1-
0?
0B
0E
0H
1K
1N
b111 *
1,
b110 &
b110 +
b110 ;
1#
#55000000
0#
#55500000
01
02
06
05
07
08
b1000 3
19
b11 I
b11 L
1>
b111111 <
1D
b10 =
b10 @
b10 C
b10 F
b10101010 :
b111 %
b111 4
1$
0)
1?
1B
1E
1H
0-
b111 &
b111 +
b111 ;
0/
0.
b0 *
0,
1#
#56000000
0#
#56500000
b0 I
b0 L
b0 O
0>
0A
0D
0G
0J
b0 <
0M
0!
0$
1-
0?
0B
0E
0H
0K
0N
0P
b1 *
1,
b0 &
b0 +
b0 ;
1#
#57000000
0#
#57500000
1!
b11 O
1J
1M
b11 I
b11 L
1>
1A
1D
b111111 <
1G
1?
1B
1E
1H
0-
b1 &
b1 +
b1 ;
1.
b10 *
0,
1#
#58000000
0#
#58500000
0!
b0 O
0J
0M
b0 I
b0 L
0>
0A
0D
b0 <
0G
1)
1-
0?
0B
0E
0H
1K
1N
b11 *
1,
b10 &
b10 +
b10 ;
1#
#59000000
0#
#59500000
1!
b11 O
1J
1M
b11 I
b11 L
1>
1A
1D
b111111 <
1G
0)
1?
1B
1E
1H
0-
b11 &
b11 +
b11 ;
1/
0.
b100 *
0,
1#
#60000000
0#
#60500000
0!
b0 I
b0 L
b0 O
0>
0A
0D
0G
0J
b0 <
0M
1-
0?
0B
0E
0H
0K
0N
1P
b101 *
1,
b100 &
b100 +
b100 ;
1#
#61000000
0#
#61500000
1!
b11 O
1J
1M
b11 I
b11 L
1>
1A
1D
b111111 <
1G
1?
1B
1E
1H
0-
b101 &
b101 +
b101 ;
1.
b110 *
0,
1#
#62000000
0#
#62500000
0!
b0 O
0J
0M
b0 I
b0 L
0>
0A
0D
b0 <
0G
1)
1-
0?
0B
0E
0H
1K
1N
b111 *
1,
b110 &
b110 +
b110 ;
1#
#63000000
0#
#63500000
16
b1001 3
15
1!
b11 O
1J
1M
b10 I
b10 L
b0 =
b11 @
b0 C
b11 F
0>
1A
0D
b111010 <
1G
b11001100 :
b1000 %
b1000 4
1$
0)
1?
1B
1E
1H
0-
b111 &
b111 +
b111 ;
0/
0.
b0 *
0,
1#
#64000000
0#
#64500000
b10 I
b10 L
b0 O
1A
1G
0J
b1010 <
0M
0!
0$
1-
0?
0B
0E
0H
0K
0N
0P
b1 *
1,
b0 &
b0 +
b0 ;
1#
#65000000
0#
#65500000
1?
1B
1E
1H
0-
b1 &
b1 +
b1 ;
1.
b10 *
0,
1#
#66000000
0#
#66500000
1!
b10 I
b10 L
b11 O
1A
1G
1J
b111010 <
1M
1)
1-
0?
0B
0E
0H
1K
1N
b11 *
1,
b10 &
b10 +
b10 ;
1#
#67000000
0#
#67500000
0)
1?
1B
1E
1H
0-
b11 &
b11 +
b11 ;
1/
0.
b100 *
0,
1#
#68000000
0#
#68500000
0!
b10 I
b10 L
b0 O
1A
1G
0J
b1010 <
0M
1-
0?
0B
0E
0H
0K
0N
1P
b101 *
1,
b100 &
b100 +
b100 ;
1#
#69000000
0#
#69500000
1?
1B
1E
1H
0-
b101 &
b101 +
b101 ;
1.
b110 *
0,
1#
#70000000
0#
#70500000
1!
b10 I
b10 L
b11 O
1A
1G
1J
b111010 <
1M
1)
1-
0?
0B
0E
0H
1K
1N
b111 *
1,
b110 &
b110 +
b110 ;
1#
#71000000
0#
#71500000
06
05
b1010 3
17
b11 I
b11 L
1>
b111111 <
1D
b10 =
b10 @
b10 C
b10 F
b10101010 :
b1001 %
b1001 4
1$
0)
1?
1B
1E
1H
0-
b111 &
b111 +
b111 ;
0/
0.
b0 *
0,
1#
#72000000
0#
#72500000
b0 I
b0 L
b0 O
0>
0A
0D
0G
0J
b0 <
0M
0!
0$
1-
0?
0B
0E
0H
0K
0N
0P
b1 *
1,
b0 &
b0 +
b0 ;
1#
#73000000
0#
#73500000
1!
b11 O
1J
1M
b11 I
b11 L
1>
1A
1D
b111111 <
1G
1?
1B
1E
1H
0-
b1 &
b1 +
b1 ;
1.
b10 *
0,
1#
#74000000
0#
#74500000
0!
b0 O
0J
0M
b0 I
b0 L
0>
0A
0D
b0 <
0G
1)
1-
0?
0B
0E
0H
1K
1N
b11 *
1,
b10 &
b10 +
b10 ;
1#
#75000000
0#
#75500000
1!
b11 O
1J
1M
b11 I
b11 L
1>
1A
1D
b111111 <
1G
0)
1?
1B
1E
1H
0-
b11 &
b11 +
b11 ;
1/
0.
b100 *
0,
1#
#76000000
0#
#76500000
0!
b0 I
b0 L
b0 O
0>
0A
0D
0G
0J
b0 <
0M
1-
0?
0B
0E
0H
0K
0N
1P
b101 *
1,
b100 &
b100 +
b100 ;
1#
#77000000
0#
#77500000
1!
b11 O
1J
1M
b11 I
b11 L
1>
1A
1D
b111111 <
1G
1?
1B
1E
1H
0-
b101 &
b101 +
b101 ;
1.
b110 *
0,
1#
#78000000
0#
#78500000
0!
b0 O
0J
0M
b0 I
b0 L
0>
0A
0D
b0 <
0G
1)
1-
0?
0B
0E
0H
1K
1N
b111 *
1,
b110 &
b110 +
b110 ;
1#
#79000000
0#
#79500000
11
16
b1011 3
15
1!
b11 O
1J
1M
b10 I
b10 L
b0 =
b11 @
b0 C
b11 F
0>
1A
0D
b111010 <
1G
b11001100 :
b1010 %
b1010 4
1$
0)
1?
1B
1E
1H
0-
b111 &
b111 +
b111 ;
0/
0.
b0 *
0,
1#
#80000000
0#
#80500000
b10 I
b10 L
b0 O
1A
1G
0J
b1010 <
0M
0!
0$
1-
0?
0B
0E
0H
0K
0N
0P
b1 *
1,
b0 &
b0 +
b0 ;
1#
#81000000
0#
#81500000
1?
1B
1E
1H
0-
b1 &
b1 +
b1 ;
1.
b10 *
0,
1#
#82000000
0#
#82500000
1!
b10 I
b10 L
b11 O
1A
1G
1J
b111010 <
1M
1)
1-
0?
0B
0E
0H
1K
1N
b11 *
1,
b10 &
b10 +
b10 ;
1#
#83000000
0#
#83500000
0)
1?
1B
1E
1H
0-
b11 &
b11 +
b11 ;
1/
0.
b100 *
0,
1#
#84000000
0#
#84500000
0!
b10 I
b10 L
b0 O
1A
1G
0J
b1010 <
0M
1-
0?
0B
0E
0H
0K
0N
1P
b101 *
1,
b100 &
b100 +
b100 ;
1#
#85000000
0#
#85500000
1?
1B
1E
1H
0-
b101 &
b101 +
b101 ;
1.
b110 *
0,
1#
#86000000
0#
#86500000
1!
b10 I
b10 L
b11 O
1A
1G
1J
b111010 <
1M
1)
1-
0?
0B
0E
0H
1K
1N
b111 *
1,
b110 &
b110 +
b110 ;
1#
#87000000
0#
#87500000
01
02
06
05
07
b1100 3
18
b11 I
b11 L
1>
b111111 <
1D
b10 =
b10 @
b10 C
b10 F
b10101010 :
b1011 %
b1011 4
1$
0)
1?
1B
1E
1H
0-
b111 &
b111 +
b111 ;
0/
0.
b0 *
0,
1#
#88000000
0#
#88500000
b0 I
b0 L
b0 O
0>
0A
0D
0G
0J
b0 <
0M
0!
0$
1-
0?
0B
0E
0H
0K
0N
0P
b1 *
1,
b0 &
b0 +
b0 ;
1#
#89000000
0#
#89500000
1!
b11 O
1J
1M
b11 I
b11 L
1>
1A
1D
b111111 <
1G
1?
1B
1E
1H
0-
b1 &
b1 +
b1 ;
1.
b10 *
0,
1#
#90000000
0#
#90500000
0!
b0 O
0J
0M
b0 I
b0 L
0>
0A
0D
b0 <
0G
1)
1-
0?
0B
0E
0H
1K
1N
b11 *
1,
b10 &
b10 +
b10 ;
1#
#91000000
0#
#91500000
1!
b11 O
1J
1M
b11 I
b11 L
1>
1A
1D
b111111 <
1G
0)
1?
1B
1E
1H
0-
b11 &
b11 +
b11 ;
1/
0.
b100 *
0,
1#
#92000000
0#
#92500000
0!
b0 I
b0 L
b0 O
0>
0A
0D
0G
0J
b0 <
0M
1-
0?
0B
0E
0H
0K
0N
1P
b101 *
1,
b100 &
b100 +
b100 ;
1#
#93000000
0#
#93500000
1!
b11 O
1J
1M
b11 I
b11 L
1>
1A
1D
b111111 <
1G
1?
1B
1E
1H
0-
b101 &
b101 +
b101 ;
1.
b110 *
0,
1#
#94000000
0#
#94500000
0!
b0 O
0J
0M
b0 I
b0 L
0>
0A
0D
b0 <
0G
1)
1-
0?
0B
0E
0H
1K
1N
b111 *
1,
b110 &
b110 +
b110 ;
1#
#95000000
0#
#95500000
16
b1101 3
15
1!
b11 O
1J
1M
b10 I
b10 L
b0 =
b11 @
b0 C
b11 F
0>
1A
0D
b111010 <
1G
b11001100 :
b1100 %
b1100 4
1$
0)
1?
1B
1E
1H
0-
b111 &
b111 +
b111 ;
0/
0.
b0 *
0,
1#
#96000000
0#
#96500000
b10 I
b10 L
b0 O
1A
1G
0J
b1010 <
0M
0!
0$
1-
0?
0B
0E
0H
0K
0N
0P
b1 *
1,
b0 &
b0 +
b0 ;
1#
#97000000
0#
#97500000
1?
1B
1E
1H
0-
b1 &
b1 +
b1 ;
1.
b10 *
0,
1#
#98000000
0#
#98500000
1!
b10 I
b10 L
b11 O
1A
1G
1J
b111010 <
1M
1)
1-
0?
0B
0E
0H
1K
1N
b11 *
1,
b10 &
b10 +
b10 ;
1#
#99000000
0#
#99500000
0)
1?
1B
1E
1H
0-
b11 &
b11 +
b11 ;
1/
0.
b100 *
0,
1#
#100000000
0#
#100500000
0!
b10 I
b10 L
b0 O
1A
1G
0J
b1010 <
0M
1-
0?
0B
0E
0H
0K
0N
1P
b101 *
1,
b100 &
b100 +
b100 ;
1#
#101000000
0#
#101500000
1?
1B
1E
1H
0-
b101 &
b101 +
b101 ;
1.
b110 *
0,
1#
#102000000
0#
#102500000
1!
b10 I
b10 L
b11 O
1A
1G
1J
b111010 <
1M
1)
1-
0?
0B
0E
0H
1K
1N
b111 *
1,
b110 &
b110 +
b110 ;
1#
#103000000
0#
#103500000
06
05
b1110 3
17
b11 I
b11 L
1>
b111111 <
1D
b10 =
b10 @
b10 C
b10 F
b10101010 :
b1101 %
b1101 4
1$
0)
1?
1B
1E
1H
0-
b111 &
b111 +
b111 ;
0/
0.
b0 *
0,
1#
#104000000
0#
#104500000
b0 I
b0 L
b0 O
0>
0A
0D
0G
0J
b0 <
0M
0!
0$
1-
0?
0B
0E
0H
0K
0N
0P
b1 *
1,
b0 &
b0 +
b0 ;
1#
#105000000
0#
#105500000
1!
b11 O
1J
1M
b11 I
b11 L
1>
1A
1D
b111111 <
1G
1?
1B
1E
1H
0-
b1 &
b1 +
b1 ;
1.
b10 *
0,
1#
#106000000
0#
#106500000
0!
b0 O
0J
0M
b0 I
b0 L
0>
0A
0D
b0 <
0G
1)
1-
0?
0B
0E
0H
1K
1N
b11 *
1,
b10 &
b10 +
b10 ;
1#
#107000000
0#
