LabTest/2019-20 Circuit Implementation/2017A7PS0080P.v
// ID: 2017A7PS0080P
// Name: VISHAL MITTAL

`timescale 1ms/1ns

module MUX_2x1(sel, in1, in2, out);
	input sel, in1, in2;
	output out;
	
	assign out = (~sel & in1) | (sel & in2);
	
endmodule


module MUX_8x1(sel, in, out);
	input[2:0] sel;
	input[7:0] in;
	output out;
	
	assign out = (sel[2] ? (sel[1] ? (sel[0] ? in[7] : in[6]) : (sel[0] ? in[5] : in[4])) : (sel[1] ? (sel[0] ? in[3] : in[2]) : (sel[0] ? in[1] : in[0])));
	
endmodule 


module MUX_ARRAY(F, C, E);
	input[7:0] F, C;
	output[7:0] E;
		
	genvar j;
	
	generate for(j = 0; j < 8; j = j+1)
		begin: mux_loop
			MUX_2x1 M2(F[j], C[j], 1'b0, E[j]);
		end
	endgenerate
	
endmodule


module COUNTER_3BIT(Q, clock, clear);
	output [2:0] Q;
	input clock, clear;

	reg [2:0] Q;
	
	initial
		Q = 3'b0;
	
	always @(posedge clock or posedge clear)
		begin
			if(clear)
				Q = 3'b0;
			else
				Q = (Q + 1) % 8;
		end
		
endmodule


module DECODER(EN, A, B);
	input EN;
	input[2:0] A;
	output[7:0] B;
	
	reg[7:0] B;
	
	always @(A)
		begin
			if(EN == 0)
				B = 8'b00000000;
			else
				begin
					case(A)
						3'b000: B = 8'b00000001;
						3'b001: B = 8'b00000010;
						3'b010: B = 8'b00000100;
						3'b011: B = 8'b00001000;
						3'b100: B = 8'b00010000;
						3'b101: B = 8'b00100000;
						3'b110: B = 8'b01000000;
						3'b111: B = 8'b10000000;
					endcase
				
				end
		end
		
endmodule


module MEMORY(S, G);
	input[2:0] S;
	output[7:0] G;
	reg[7:0] mem[0:7];
	
	reg[7:0] G;
	
	//Initialize the memory
	initial
	begin
		 mem[0] = 8'b00000001;  //2'h01;
		 mem[1] = 8'b00000011;  //2'h03;
		 mem[2] = 8'b00000111;  //2'h07;
		 mem[3] = 8'b00001111;  //2'h0F;
		 mem[4] = 8'b00011111;  //2'h1F;
		 mem[5] = 8'b00111111;  //2'h3F;
		 mem[6] = 8'b01111111;  //2'h7F;
		 mem[7] = 8'b11111111;  //2'hFF;
	end
	
	always @(S)
		begin
			case(S)
				3'b000: G = mem[0];
				3'b001: G = mem[1];
				3'b010: G = mem[2];
				3'b011: G = mem[3];
				3'b100: G = mem[4];
				3'b101: G = mem[5];
				3'b110: G = mem[6];
				3'b111: G = mem[7];
			endcase
		
		end
	
endmodule


module TOP_MODULE(clock, clear, S, EN, OUT);
	input clock, clear, EN;
	input[2:0] S;
	output OUT;
	
	wire[2:0] Q;
	wire[7:0] B, G, E;
	
	MUX_8x1 M8(Q, E, OUT);
	MUX_ARRAY MA(G, B, E);
	COUNTER_3BIT CNTR3(Q, clock, clear);
	DECODER DEC(EN, Q, B);
	MEMORY MEM(S, G);
	
endmodule



module TESTBENCH;

	initial	
	begin
		$dumpfile("2017A7PS0080P.vcd");
		$dumpvars;
	end
	
	reg clock, clear, EN;
	reg[2:0] S;
	wire OUT;
	
	TOP_MODULE TM(clock, clear, S, EN, OUT);
	
	initial
		clock = 1'b0;
	
	always
		#0.5 clock <= ~clock;
	
	initial
		begin
			$monitor($time, " S = %b, Clear = %b, Output = %b", S, clear, OUT);
			clear = 1'b1;  //clear the counter
			EN = 1;
			S = 3'b000;
			#2 clear = 1'b0;  
			#8 S = 3'b001;
			#8 S = 3'b010;
			#8 S = 3'b011;
			#8 S = 3'b100;
			#8 S = 3'b101;
			#8 S = 3'b110;
			#8 S = 3'b111;
			#8 $finish;			
		end
	
endmodule

LabTest/2019-20 Circuit Implementation/2017A7PS0080P.vcd
$date
	Sun Nov 10 22:13:22 2019
$end
$version
	Icarus Verilog
$end
$timescale
	1ns
$end
$scope module TESTBENCH $end
$var wire 1 ! OUT $end
$var reg 1 " EN $end
$var reg 3 # S [2:0] $end
$var reg 1 $ clear $end
$var reg 1 % clock $end
$scope module TM $end
$var wire 1 " EN $end
$var wire 3 & S [2:0] $end
$var wire 1 $ clear $end
$var wire 1 % clock $end
$var wire 3 ' Q [2:0] $end
$var wire 1 ! OUT $end
$var wire 8 ( G [7:0] $end
$var wire 8 ) E [7:0] $end
$var wire 8 * B [7:0] $end
$scope module CNTR3 $end
$var wire 1 $ clear $end
$var wire 1 % clock $end
$var reg 3 + Q [2:0] $end
$upscope $end
$scope module DEC $end
$var wire 3 , A [2:0] $end
$var wire 1 " EN $end
$var reg 8 - B [7:0] $end
$upscope $end
$scope module M8 $end
$var wire 3 . sel [2:0] $end
$var wire 1 ! out $end
$var wire 8 / in [7:0] $end
$upscope $end
$scope module MA $end
$var wire 8 0 C [7:0] $end
$var wire 8 1 F [7:0] $end
$var wire 8 2 E [7:0] $end
$scope begin mux_loop[0] $end
$scope module M2 $end
$var wire 1 3 in1 $end
$var wire 1 4 in2 $end
$var wire 1 5 out $end
$var wire 1 6 sel $end
$upscope $end
$upscope $end
$scope begin mux_loop[1] $end
$scope module M2 $end
$var wire 1 7 in1 $end
$var wire 1 8 in2 $end
$var wire 1 9 out $end
$var wire 1 : sel $end
$upscope $end
$upscope $end
$scope begin mux_loop[2] $end
$scope module M2 $end
$var wire 1 ; in1 $end
$var wire 1 < in2 $end
$var wire 1 = out $end
$var wire 1 > sel $end
$upscope $end
$upscope $end
$scope begin mux_loop[3] $end
$scope module M2 $end
$var wire 1 ? in1 $end
$var wire 1 @ in2 $end
$var wire 1 A out $end
$var wire 1 B sel $end
$upscope $end
$upscope $end
$scope begin mux_loop[4] $end
$scope module M2 $end
$var wire 1 C in1 $end
$var wire 1 D in2 $end
$var wire 1 E out $end
$var wire 1 F sel $end
$upscope $end
$upscope $end
$scope begin mux_loop[5] $end
$scope module M2 $end
$var wire 1 G in1 $end
$var wire 1 H in2 $end
$var wire 1 I out $end
$var wire 1 J sel $end
$upscope $end
$upscope $end
$scope begin mux_loop[6] $end
$scope module M2 $end
$var wire 1 K in1 $end
$var wire 1 L in2 $end
$var wire 1 M out $end
$var wire 1 N sel $end
$upscope $end
$upscope $end
$scope begin mux_loop[7] $end
$scope module M2 $end
$var wire 1 O in1 $end
$var wire 1 P in2 $end
$var wire 1 Q out $end
$var wire 1 R sel $end
$upscope $end
$upscope $end
$upscope $end
$scope module MEM $end
$var wire 3 S S [2:0] $end
$var reg 8 T G [7:0] $end
$upscope $end
$upscope $end
$upscope $end
$enddefinitions $end
#0
$dumpvars
b1 T
b0 S
0R
0Q
0P
0O
0N
0M
0L
0K
0J
0I
0H
0G
0F
0E
0D
0C
0B
0A
0@
0?
0>
0=
0<
0;
0:
09
08
07
16
05
04
13
b0 2
b1 1
b1 0
b0 /
b0 .
b1 -
b0 ,
b0 +
b1 *
b0 )
b1 (
b0 '
b0 &
0%
1$
b0 #
1"
0!
$end
#500000
1%
#1000000
0%
#1500000
1%
#2000000
0%
0$
#2500000
1!
b10 )
b10 /
b10 2
19
03
17
b10 *
b10 -
b10 0
b1 '
b1 +
b1 ,
b1 .
1%
#3000000
0%
#3500000
09
b100 )
b100 /
b100 2
1=
1!
07
1;
b100 *
b100 -
b100 0
b10 '
b10 +
b10 ,
b10 .
1%
#4000000
0%
#4500000
0=
b1000 )
b1000 /
b1000 2
1A
1!
0;
1?
b1000 *
b1000 -
b1000 0
b11 '
b11 +
b11 ,
b11 .
1%
#5000000
0%
#5500000
0A
b10000 )
b10000 /
b10000 2
1E
0?
1C
1!
b10000 *
b10000 -
b10000 0
b100 '
b100 +
b100 ,
b100 .
1%
#6000000
0%
#6500000
0E
b100000 )
b100000 /
b100000 2
1I
1!
0C
1G
b100000 *
b100000 -
b100000 0
b101 '
b101 +
b101 ,
b101 .
1%
#7000000
0%
#7500000
0I
b1000000 )
b1000000 /
b1000000 2
1M
1!
0G
1K
b1000000 *
b1000000 -
b1000000 0
b110 '
b110 +
b110 ,
b110 .
1%
#8000000
0%
#8500000
0M
b10000000 )
b10000000 /
b10000000 2
1Q
1!
0K
1O
b10000000 *
b10000000 -
b10000000 0
b111 '
b111 +
b111 ,
b111 .
1%
#9000000
0%
#9500000
b0 )
b0 /
b0 2
0Q
13
0O
0!
b1 *
b1 -
b1 0
b0 '
b0 +
b0 ,
b0 .
1%
#10000000
0%
1:
b11 (
b11 1
b11 T
b1 #
b1 &
b1 S
#10500000
03
17
b10 *
b10 -
b10 0
b1 '
b1 +
b1 ,
b1 .
1%
#11000000
0%
#11500000
1!
b100 )
b100 /
b100 2
1=
07
1;
b100 *
b100 -
b100 0
b10 '
b10 +
b10 ,
b10 .
1%
#12000000
0%
#12500000
0=
b1000 )
b1000 /
b1000 2
1A
1!
0;
1?
b1000 *
b1000 -
b1000 0
b11 '
b11 +
b11 ,
b11 .
1%
#13000000
0%
#13500000
0A
b10000 )
b10000 /
b10000 2
1E
0?
1C
1!
b10000 *
b10000 -
b10000 0
b100 '
b100 +
b100 ,
b100 .
1%
#14000000
0%
#14500000
0E
b100000 )
b100000 /
b100000 2
1I
1!
0C
1G
b100000 *
b100000 -
b100000 0
b101 '
b101 +
b101 ,
b101 .
1%
#15000000
0%
#15500000
0I
b1000000 )
b1000000 /
b1000000 2
1M
1!
0G
1K
b1000000 *
b1000000 -
b1000000 0
b110 '
b110 +
b110 ,
b110 .
1%
#16000000
0%
#16500000
0M
b10000000 )
b10000000 /
b10000000 2
1Q
1!
0K
1O
b10000000 *
b10000000 -
b10000000 0
b111 '
b111 +
b111 ,
b111 .
1%
#17000000
0%
#17500000
b0 )
b0 /
b0 2
0Q
13
0O
0!
b1 *
b1 -
b1 0
b0 '
b0 +
b0 ,
b0 .
1%
#18000000
0%
1>
b111 (
b111 1
b111 T
b10 #
b10 &
b10 S
#18500000
03
17
b10 *
b10 -
b10 0
b1 '
b1 +
b1 ,
b1 .
1%
#19000000
0%
#19500000
07
1;
b100 *
b100 -
b100 0
b10 '
b10 +
b10 ,
b10 .
1%
#20000000
0%
#20500000
1!
b1000 )
b1000 /
b1000 2
1A
0;
1?
b1000 *
b1000 -
b1000 0
b11 '
b11 +
b11 ,
b11 .
1%
#21000000
0%
#21500000
0A
b10000 )
b10000 /
b10000 2
1E
0?
1C
1!
b10000 *
b10000 -
b10000 0
b100 '
b100 +
b100 ,
b100 .
1%
#22000000
0%
#22500000
0E
b100000 )
b100000 /
b100000 2
1I
1!
0C
1G
b100000 *
b100000 -
b100000 0
b101 '
b101 +
b101 ,
b101 .
1%
#23000000
0%
#23500000
0I
b1000000 )
b1000000 /
b1000000 2
1M
1!
0G
1K
b1000000 *
b1000000 -
b1000000 0
b110 '
b110 +
b110 ,
b110 .
1%
#24000000
0%
#24500000
0M
b10000000 )
b10000000 /
b10000000 2
1Q
1!
0K
1O
b10000000 *
b10000000 -
b10000000 0
b111 '
b111 +
b111 ,
b111 .
1%
#25000000
0%
#25500000
b0 )
b0 /
b0 2
0Q
13
0O
0!
b1 *
b1 -
b1 0
b0 '
b0 +
b0 ,
b0 .
1%
#26000000
0%
1B
b1111 (
b1111 1
b1111 T
b11 #
b11 &
b11 S
#26500000
03
17
b10 *
b10 -
b10 0
b1 '
b1 +
b1 ,
b1 .
1%
#27000000
0%
#27500000
07
1;
b100 *
b100 -
b100 0
b10 '
b10 +
b10 ,
b10 .
1%
#28000000
0%
#28500000
0;
1?
b1000 *
b1000 -
b1000 0
b11 '
b11 +
b11 ,
b11 .
1%
#29000000
0%
#29500000
1!
b10000 )
b10000 /
b10000 2
1E
0?
1C
b10000 *
b10000 -
b10000 0
b100 '
b100 +
b100 ,
b100 .
1%
#30000000
0%
#30500000
0E
b100000 )
b100000 /
b100000 2
1I
1!
0C
1G
b100000 *
b100000 -
b100000 0
b101 '
b101 +
b101 ,
b101 .
1%
#31000000
0%
#31500000
0I
b1000000 )
b1000000 /
b1000000 2
1M
1!
0G
1K
b1000000 *
b1000000 -
b1000000 0
b110 '
b110 +
b110 ,
b110 .
1%
#32000000
0%
#32500000
0M
b10000000 )
b10000000 /
b10000000 2
1Q
1!
0K
1O
b10000000 *
b10000000 -
b10000000 0
b111 '
b111 +
b111 ,
b111 .
1%
#33000000
0%
#33500000
b0 )
b0 /
b0 2
0Q
13
0O
0!
b1 *
b1 -
b1 0
b0 '
b0 +
b0 ,
b0 .
1%
#34000000
0%
1F
b11111 (
b11111 1
b11111 T
b100 #
b100 &
b100 S
#34500000
03
17
b10 *
b10 -
b10 0
b1 '
b1 +
b1 ,
b1 .
1%
#35000000
0%
#35500000
07
1;
b100 *
b100 -
b100 0
b10 '
b10 +
b10 ,
b10 .
1%
#36000000
0%
#36500000
0;
1?
b1000 *
b1000 -
b1000 0
b11 '
b11 +
b11 ,
b11 .
1%
#37000000
0%
#37500000
0?
1C
b10000 *
b10000 -
b10000 0
b100 '
b100 +
b100 ,
b100 .
1%
#38000000
0%
#38500000
1!
b100000 )
b100000 /
b100000 2
1I
0C
1G
b100000 *
b100000 -
b100000 0
b101 '
b101 +
b101 ,
b101 .
1%
#39000000
0%
#39500000
0I
b1000000 )
b1000000 /
b1000000 2
1M
1!
0G
1K
b1000000 *
b1000000 -
b1000000 0
b110 '
b110 +
b110 ,
b110 .
1%
#40000000
0%
#40500000
0M
b10000000 )
b10000000 /
b10000000 2
1Q
1!
0K
1O
b10000000 *
b10000000 -
b10000000 0
b111 '
b111 +
b111 ,
b111 .
1%
#41000000
0%
#41500000
b0 )
b0 /
b0 2
0Q
13
0O
0!
b1 *
b1 -
b1 0
b0 '
b0 +
b0 ,
b0 .
1%
#42000000
0%
1J
b111111 (
b111111 1
b111111 T
b101 #
b101 &
b101 S
#42500000
03
17
b10 *
b10 -
b10 0
b1 '
b1 +
b1 ,
b1 .
1%
#43000000
0%
#43500000
07
1;
b100 *
b100 -
b100 0
b10 '
b10 +
b10 ,
b10 .
1%
#44000000
0%
#44500000
0;
1?
b1000 *
b1000 -
b1000 0
b11 '
b11 +
b11 ,
b11 .
1%
#45000000
0%
#45500000
0?
1C
b10000 *
b10000 -
b10000 0
b100 '
b100 +
b100 ,
b100 .
1%
#46000000
0%
#46500000
0C
1G
b100000 *
b100000 -
b100000 0
b101 '
b101 +
b101 ,
b101 .
1%
#47000000
0%
#47500000
1!
b1000000 )
b1000000 /
b1000000 2
1M
0G
1K
b1000000 *
b1000000 -
b1000000 0
b110 '
b110 +
b110 ,
b110 .
1%
#48000000
0%
#48500000
0M
b10000000 )
b10000000 /
b10000000 2
1Q
1!
0K
1O
b10000000 *
b10000000 -
b10000000 0
b111 '
b111 +
b111 ,
b111 .
1%
#49000000
0%
#49500000
b0 )
b0 /
b0 2
0Q
13
0O
0!
b1 *
b1 -
b1 0
b0 '
b0 +
b0 ,
b0 .
1%
#50000000
0%
1N
b1111111 (
b1111111 1
b1111111 T
b110 #
b110 &
b110 S
#50500000
03
17
b10 *
b10 -
b10 0
b1 '
b1 +
b1 ,
b1 .
1%
#51000000
0%
#51500000
07
1;
b100 *
b100 -
b100 0
b10 '
b10 +
b10 ,
b10 .
1%
#52000000
0%
#52500000
0;
1?
b1000 *
b1000 -
b1000 0
b11 '
b11 +
b11 ,
b11 .
1%
#53000000
0%
#53500000
0?
1C
b10000 *
b10000 -
b10000 0
b100 '
b100 +
b100 ,
b100 .
1%
#54000000
0%
#54500000
0C
1G
b100000 *
b100000 -
b100000 0
b101 '
b101 +
b101 ,
b101 .
1%
#55000000
0%
#55500000
0G
1K
b1000000 *
b1000000 -
b1000000 0
b110 '
b110 +
b110 ,
b110 .
1%
#56000000
0%
#56500000
1!
b10000000 )
b10000000 /
b10000000 2
1Q
0K
1O
b10000000 *
b10000000 -
b10000000 0
b111 '
b111 +
b111 ,
b111 .
1%
#57000000
0%
#57500000
b0 )
b0 /
b0 2
0Q
13
0O
0!
b1 *
b1 -
b1 0
b0 '
b0 +
b0 ,
b0 .
1%
#58000000
0%
1R
b11111111 (
b11111111 1
b11111111 T
b111 #
b111 &
b111 S
#58500000
03
17
b10 *
b10 -
b10 0
b1 '
b1 +
b1 ,
b1 .
1%
#59000000
0%
#59500000
07
1;
b100 *
b100 -
b100 0
b10 '
b10 +
b10 ,
b10 .
1%
#60000000
0%
#60500000
0;
1?
b1000 *
b1000 -
b1000 0
b11 '
b11 +
b11 ,
b11 .
1%
#61000000
0%
#61500000
0?
1C
b10000 *
b10000 -
b10000 0
b100 '
b100 +
b100 ,
b100 .
1%
#62000000
0%
#62500000
0C
1G
b100000 *
b100000 -
b100000 0
b101 '
b101 +
b101 ,
b101 .
1%
#63000000
0%
#63500000
0G
1K
b1000000 *
b1000000 -
b1000000 0
b110 '
b110 +
b110 ,
b110 .
1%
#64000000
0%
#64500000
0K
1O
b10000000 *
b10000000 -
b10000000 0
b111 '
b111 +
b111 ,
b111 .
1%
#65000000
0%
#65500000
13
0O
b1 *
b1 -
b1 0
b0 '
b0 +
b0 ,
b0 .
1%
