LabTest/2018-19 ASM/file.v
`timescale 1ms/1ns
/*Behavioral*/
module dff(
	output q,
	input d,
	input clk,
	input reset,
	input set
);
	
	reg q;

	initial
		q = 1'b0;

	always @(posedge clk or set) 
	begin
		case ({reset, set})
			2'b00: q <= d;
			2'b01: q <= 1'b1;
			2'b10: q <= 1'b0;
			2'b11: q <= 1'bz;
		endcase
	end

endmodule

module tff(
	output q,
	input t,
	input clk,
	input reset
);
	reg q;
	initial 
		q <= 1'b0;
	always @(posedge clk) begin
		if(reset)
			q <= 1'b0;
		else
			if( t == 0)
				q <= q;
			else 
				q <= ~q;
	end

endmodule

module counter4bit(
	output [3:0] q,
	input clock,
	input rst,
	input en
);
	wire clk;
	wire [3:0] t;
	assign t[0] = 1'b1;
	assign t[1] = q[0];
	and(t[2], q[1], q[0]);
	and(t[3], q[2], t[2]);

	assign clk = clock & en;

	tff ff1(q[0], t[0], clk, rst);
	tff ff2(q[1], t[1], clk, rst);
	tff ff3(q[2], t[2], clk, rst);
	tff ff4(q[3], t[3], clk, rst);

endmodule

/*Gate Lvl*/
module ctrlLogic(
	output t0,
	output t1,
	output t2,
	input clk,
	input s,
	input z,
	input x,
	input set
);
	// reg t0;
	// initial 
	// 	t0 = 1'b1;
	wire dt0, dt1, dt2, t0, t1, t2;
	wire sbar, zbar, xbar;
	wire t0and1, t0and2, t0or1;
	wire t1and1, t1and2, t1and3, t1or1, t1or2;
	wire t2and1, t2and2, t2or1;
	
	not(sbar,s);
	not(zbar,z);
	not(xbar,x);

	and(t0and1, t0, sbar);
	and(t0and2, t2, z);
	or(t0or1, t0and1, t0and2);

	and(t1and1, t0, s);
	and(t1and2, t2, xbar, zbar);
	and(t1and3, t1, xbar);
	or(t1or1, t1and1, t1and2);
	or(t1or2, t1or1, t1and3);

	and(t2and1, t1, x);
	and(t2and2, t2, x, zbar);
	or(t2or1, t2and1, t2and2);
		
	dff ff1(t0,t0or1,clk, 1'b0, set);
	dff ff2(t1,t1or2,clk, 1'b0, 1'b0);
	dff ff3(t2,t2or1,clk, 1'b0, 1'b0);

endmodule

module intg(
	output [3:0] q,
	output g,
	input s,
	input xx,
	input clk,
	input set
);
	
	wire rst;
	wire en;
	wire [2:0] t;
	wire zz;

	assign rst = t[0] & s;
	assign en = (t[1] & xx) | (t[2] & (~zz) & xx);
	
	wire [3:0] q;
	counter4bit ctr(q, clk, rst, en);

	assign zz = q[0] & q[1] & q[2] & q[3];
	ctrlLogic ctrl(t[0], t[1], t[2], clk, s, zz, xx, set);
	
	wire d;
	assign d = zz & t[2];
	dff ff(g, d, clk, rst, 1'b0);	

endmodule

module tb_intg();
	
	reg clk;
	initial 
		clk = 1'b0;
	always
	#0.5 clk = ~clk;
	
	reg s;
	reg xx;
	reg set;
	wire [3:0] q;
	wire g;

	intg mod(q, g, s, xx, clk, set);

	initial begin
			set = 1'b1;
			s = 1'b0;
			xx = 1'b0;
		#5	s = 1'b1;
			set = 1'b0;
			xx = 1'b1;
		#100 $finish;

	end	
	initial begin
		$dumpfile("file.vcd");
		$dumpvars;
	end

	initial begin
		$monitor("s = %b, x = %b, q = %d, g = %b", s, xx, q, g);
	end

endmodule

LabTest/2018-19 ASM/file.vcd
$date
	Sun Nov 10 12:00:55 2019
$end
$version
	Icarus Verilog
$end
$timescale
	1ns
$end
$scope module tb_intg $end
$var wire 4 ! q [3:0] $end
$var wire 1 " g $end
$var reg 1 # clk $end
$var reg 1 $ s $end
$var reg 1 % set $end
$var reg 1 & xx $end
$scope module mod $end
$var wire 1 # clk $end
$var wire 1 ' d $end
$var wire 1 ( en $end
$var wire 1 ) rst $end
$var wire 1 $ s $end
$var wire 1 % set $end
$var wire 1 & xx $end
$var wire 1 * zz $end
$var wire 3 + t [2:0] $end
$var wire 4 , q [3:0] $end
$var wire 1 " g $end
$scope module ctr $end
$var wire 1 - clk $end
$var wire 1 # clock $end
$var wire 1 ( en $end
$var wire 1 ) rst $end
$var wire 4 . t [3:0] $end
$var wire 4 / q [3:0] $end
$scope module ff1 $end
$var wire 1 - clk $end
$var wire 1 ) reset $end
$var wire 1 0 t $end
$var reg 1 1 q $end
$upscope $end
$scope module ff2 $end
$var wire 1 - clk $end
$var wire 1 ) reset $end
$var wire 1 2 t $end
$var reg 1 3 q $end
$upscope $end
$scope module ff3 $end
$var wire 1 - clk $end
$var wire 1 ) reset $end
$var wire 1 4 t $end
$var reg 1 5 q $end
$upscope $end
$scope module ff4 $end
$var wire 1 - clk $end
$var wire 1 ) reset $end
$var wire 1 6 t $end
$var reg 1 7 q $end
$upscope $end
$upscope $end
$scope module ctrl $end
$var wire 1 # clk $end
$var wire 1 $ s $end
$var wire 1 8 sbar $end
$var wire 1 % set $end
$var wire 1 9 t0and1 $end
$var wire 1 : t0and2 $end
$var wire 1 ; t0or1 $end
$var wire 1 < t1and1 $end
$var wire 1 = t1and2 $end
$var wire 1 > t1and3 $end
$var wire 1 ? t1or1 $end
$var wire 1 @ t1or2 $end
$var wire 1 A t2and1 $end
$var wire 1 B t2and2 $end
$var wire 1 C t2or1 $end
$var wire 1 & x $end
$var wire 1 D xbar $end
$var wire 1 * z $end
$var wire 1 E zbar $end
$var wire 1 F t2 $end
$var wire 1 G t1 $end
$var wire 1 H t0 $end
$scope module ff1 $end
$var wire 1 # clk $end
$var wire 1 ; d $end
$var wire 1 I reset $end
$var wire 1 % set $end
$var reg 1 H q $end
$upscope $end
$scope module ff2 $end
$var wire 1 # clk $end
$var wire 1 @ d $end
$var wire 1 J reset $end
$var wire 1 K set $end
$var reg 1 G q $end
$upscope $end
$scope module ff3 $end
$var wire 1 # clk $end
$var wire 1 C d $end
$var wire 1 L reset $end
$var wire 1 M set $end
$var reg 1 F q $end
$upscope $end
$upscope $end
$scope module ff $end
$var wire 1 # clk $end
$var wire 1 ' d $end
$var wire 1 ) reset $end
$var wire 1 N set $end
$var reg 1 " q $end
$upscope $end
$upscope $end
$upscope $end
$enddefinitions $end
#0
$dumpvars
0N
0M
0L
0K
0J
0I
1H
0G
0F
1E
1D
0C
0B
0A
0@
0?
0>
0=
0<
1;
0:
19
18
07
06
05
04
03
02
01
10
b0 /
b1 .
0-
b0 ,
b1 +
0*
0)
0(
0'
0&
1%
0$
0#
0"
b0 !
$end
#500000
1#
#1000000
0#
#1500000
1#
#2000000
0#
#2500000
1#
#3000000
0#
#3500000
1#
#4000000
0#
#4500000
1#
#5000000
0;
1@
09
1?
0D
1)
08
1<
0#
1&
0%
1$
#5500000
12
b11 .
b1 !
b1 ,
b1 /
11
1-
0@
1(
0?
0)
1C
0<
1A
0H
b10 +
1G
1#
#6000000
0-
0#
#6500000
02
b1 .
0A
1B
13
b10 !
b10 ,
b10 /
01
0G
b100 +
1F
1-
1#
#7000000
0-
0#
#7500000
14
12
b111 .
b11 !
b11 ,
b11 /
11
1-
1#
#8000000
0-
0#
#8500000
06
04
02
b1 .
15
03
b100 !
b100 ,
b100 /
01
1-
1#
#9000000
0-
0#
#9500000
12
b11 .
b101 !
b101 ,
b101 /
11
1-
1#
#10000000
0-
0#
#10500000
02
b1 .
13
b110 !
b110 ,
b110 /
01
1-
1#
#11000000
0-
0#
#11500000
16
14
12
b1111 .
b111 !
b111 ,
b111 /
11
1-
1#
#12000000
0-
0#
#12500000
06
04
02
b1 .
17
05
03
b1000 !
b1000 ,
b1000 /
01
1-
1#
#13000000
0-
0#
#13500000
12
b11 .
b1001 !
b1001 ,
b1001 /
11
1-
1#
#14000000
0-
0#
#14500000
02
b1 .
13
b1010 !
b1010 ,
b1010 /
01
1-
1#
#15000000
0-
0#
#15500000
14
12
b111 .
b1011 !
b1011 ,
b1011 /
11
1-
1#
#16000000
0-
0#
#16500000
06
04
02
b1 .
15
03
b1100 !
b1100 ,
b1100 /
01
1-
1#
#17000000
0-
0#
#17500000
12
b11 .
b1101 !
b1101 ,
b1101 /
11
1-
1#
#18000000
0-
0#
#18500000
02
b1 .
13
b1110 !
b1110 ,
b1110 /
01
1-
1#
#19000000
0-
0#
#19500000
0(
0C
0B
1;
16
1'
0E
1:
1*
14
12
b1111 .
b1111 !
b1111 ,
b1111 /
11
0-
1#
#20000000
0#
#20500000
1@
1?
1)
0;
0'
1<
0:
1H
b1 +
0F
1"
1#
#21000000
0#
#21500000
1E
06
04
0*
02
b1 .
07
05
03
b0 !
b0 ,
b0 /
01
1-
0@
1(
0?
0)
1C
0<
1A
0H
b10 +
1G
0"
1#
#22000000
0-
0#
#22500000
12
b11 .
0A
1B
b1 !
b1 ,
b1 /
11
0G
b100 +
1F
1-
1#
#23000000
0-
0#
#23500000
02
b1 .
13
b10 !
b10 ,
b10 /
01
1-
1#
#24000000
0-
0#
#24500000
14
12
b111 .
b11 !
b11 ,
b11 /
11
1-
1#
#25000000
0-
0#
#25500000
06
04
02
b1 .
15
03
b100 !
b100 ,
b100 /
01
1-
1#
#26000000
0-
0#
#26500000
12
b11 .
b101 !
b101 ,
b101 /
11
1-
1#
#27000000
0-
0#
#27500000
02
b1 .
13
b110 !
b110 ,
b110 /
01
1-
1#
#28000000
0-
0#
#28500000
16
14
12
b1111 .
b111 !
b111 ,
b111 /
11
1-
1#
#29000000
0-
0#
#29500000
06
04
02
b1 .
17
05
03
b1000 !
b1000 ,
b1000 /
01
1-
1#
#30000000
0-
0#
#30500000
12
b11 .
b1001 !
b1001 ,
b1001 /
11
1-
1#
#31000000
0-
0#
#31500000
02
b1 .
13
b1010 !
b1010 ,
b1010 /
01
1-
1#
#32000000
0-
0#
#32500000
14
12
b111 .
b1011 !
b1011 ,
b1011 /
11
1-
1#
#33000000
0-
0#
#33500000
06
04
02
b1 .
15
03
b1100 !
b1100 ,
b1100 /
01
1-
1#
#34000000
0-
0#
#34500000
12
b11 .
b1101 !
b1101 ,
b1101 /
11
1-
1#
#35000000
0-
0#
#35500000
02
b1 .
13
b1110 !
b1110 ,
b1110 /
01
1-
1#
#36000000
0-
0#
#36500000
0(
0C
0B
1;
16
1'
0E
1:
1*
14
12
b1111 .
b1111 !
b1111 ,
b1111 /
11
0-
1#
#37000000
0#
#37500000
1@
1?
1)
0;
0'
1<
0:
1H
b1 +
0F
1"
1#
#38000000
0#
#38500000
1E
06
04
0*
02
b1 .
07
05
03
b0 !
b0 ,
b0 /
01
1-
0@
1(
0?
0)
1C
0<
1A
0H
b10 +
1G
0"
1#
#39000000
0-
0#
#39500000
12
b11 .
0A
1B
b1 !
b1 ,
b1 /
11
0G
b100 +
1F
1-
1#
#40000000
0-
0#
#40500000
02
b1 .
13
b10 !
b10 ,
b10 /
01
1-
1#
#41000000
0-
0#
#41500000
14
12
b111 .
b11 !
b11 ,
b11 /
11
1-
1#
#42000000
0-
0#
#42500000
06
04
02
b1 .
15
03
b100 !
b100 ,
b100 /
01
1-
1#
#43000000
0-
0#
#43500000
12
b11 .
b101 !
b101 ,
b101 /
11
1-
1#
#44000000
0-
0#
#44500000
02
b1 .
13
b110 !
b110 ,
b110 /
01
1-
1#
#45000000
0-
0#
#45500000
16
14
12
b1111 .
b111 !
b111 ,
b111 /
11
1-
1#
#46000000
0-
0#
#46500000
06
04
02
b1 .
17
05
03
b1000 !
b1000 ,
b1000 /
01
1-
1#
#47000000
0-
0#
#47500000
12
b11 .
b1001 !
b1001 ,
b1001 /
11
1-
1#
#48000000
0-
0#
#48500000
02
b1 .
13
b1010 !
b1010 ,
b1010 /
01
1-
1#
#49000000
0-
0#
#49500000
14
12
b111 .
b1011 !
b1011 ,
b1011 /
11
1-
1#
#50000000
0-
0#
#50500000
06
04
02
b1 .
15
03
b1100 !
b1100 ,
b1100 /
01
1-
1#
#51000000
0-
0#
#51500000
12
b11 .
b1101 !
b1101 ,
b1101 /
11
1-
1#
#52000000
0-
0#
#52500000
02
b1 .
13
b1110 !
b1110 ,
b1110 /
01
1-
1#
#53000000
0-
0#
#53500000
0(
0C
0B
1;
16
1'
0E
1:
1*
14
12
b1111 .
b1111 !
b1111 ,
b1111 /
11
0-
1#
#54000000
0#
#54500000
1@
1?
1)
0;
0'
1<
0:
1H
b1 +
0F
1"
1#
#55000000
0#
#55500000
1E
06
04
0*
02
b1 .
07
05
03
b0 !
b0 ,
b0 /
01
1-
0@
1(
0?
0)
1C
0<
1A
0H
b10 +
1G
0"
1#
#56000000
0-
0#
#56500000
12
b11 .
0A
1B
b1 !
b1 ,
b1 /
11
0G
b100 +
1F
1-
1#
#57000000
0-
0#
#57500000
02
b1 .
13
b10 !
b10 ,
b10 /
01
1-
1#
#58000000
0-
0#
#58500000
14
12
b111 .
b11 !
b11 ,
b11 /
11
1-
1#
#59000000
0-
0#
#59500000
06
04
02
b1 .
15
03
b100 !
b100 ,
b100 /
01
1-
1#
#60000000
0-
0#
#60500000
12
b11 .
b101 !
b101 ,
b101 /
11
1-
1#
#61000000
0-
0#
#61500000
02
b1 .
13
b110 !
b110 ,
b110 /
01
1-
1#
#62000000
0-
0#
#62500000
16
14
12
b1111 .
b111 !
b111 ,
b111 /
11
1-
1#
#63000000
0-
0#
#63500000
06
04
02
b1 .
17
05
03
b1000 !
b1000 ,
b1000 /
01
1-
1#
#64000000
0-
0#
#64500000
12
b11 .
b1001 !
b1001 ,
b1001 /
11
1-
1#
#65000000
0-
0#
#65500000
02
b1 .
13
b1010 !
b1010 ,
b1010 /
01
1-
1#
#66000000
0-
0#
#66500000
14
12
b111 .
b1011 !
b1011 ,
b1011 /
11
1-
1#
#67000000
0-
0#
#67500000
06
04
02
b1 .
15
03
b1100 !
b1100 ,
b1100 /
01
1-
1#
#68000000
0-
0#
#68500000
12
b11 .
b1101 !
b1101 ,
b1101 /
11
1-
1#
#69000000
0-
0#
#69500000
02
b1 .
13
b1110 !
b1110 ,
b1110 /
01
1-
1#
#70000000
0-
0#
#70500000
0(
0C
0B
1;
16
1'
0E
1:
1*
14
12
b1111 .
b1111 !
b1111 ,
b1111 /
11
0-
1#
#71000000
0#
#71500000
1@
1?
1)
0;
0'
1<
0:
1H
b1 +
0F
1"
1#
#72000000
0#
#72500000
1E
06
04
0*
02
b1 .
07
05
03
b0 !
b0 ,
b0 /
01
1-
0@
1(
0?
0)
1C
0<
1A
0H
b10 +
1G
0"
1#
#73000000
0-
0#
#73500000
12
b11 .
0A
1B
b1 !
b1 ,
b1 /
11
0G
b100 +
1F
1-
1#
#74000000
0-
0#
#74500000
02
b1 .
13
b10 !
b10 ,
b10 /
01
1-
1#
#75000000
0-
0#
#75500000
14
12
b111 .
b11 !
b11 ,
b11 /
11
1-
1#
#76000000
0-
0#
#76500000
06
04
02
b1 .
15
03
b100 !
b100 ,
b100 /
01
1-
1#
#77000000
0-
0#
#77500000
12
b11 .
b101 !
b101 ,
b101 /
11
1-
1#
#78000000
0-
0#
#78500000
02
b1 .
13
b110 !
b110 ,
b110 /
01
1-
1#
#79000000
0-
0#
#79500000
16
14
12
b1111 .
b111 !
b111 ,
b111 /
11
1-
1#
#80000000
0-
0#
#80500000
06
04
02
b1 .
17
05
03
b1000 !
b1000 ,
b1000 /
01
1-
1#
#81000000
0-
0#
#81500000
12
b11 .
b1001 !
b1001 ,
b1001 /
11
1-
1#
#82000000
0-
0#
#82500000
02
b1 .
13
b1010 !
b1010 ,
b1010 /
01
1-
1#
#83000000
0-
0#
#83500000
14
12
b111 .
b1011 !
b1011 ,
b1011 /
11
1-
1#
#84000000
0-
0#
#84500000
06
04
02
b1 .
15
03
b1100 !
b1100 ,
b1100 /
01
1-
1#
#85000000
0-
0#
#85500000
12
b11 .
b1101 !
b1101 ,
b1101 /
11
1-
1#
#86000000
0-
0#
#86500000
02
b1 .
13
b1110 !
b1110 ,
b1110 /
01
1-
1#
#87000000
0-
0#
#87500000
0(
0C
0B
1;
16
1'
0E
1:
1*
14
12
b1111 .
b1111 !
b1111 ,
b1111 /
11
0-
1#
#88000000
0#
#88500000
1@
1?
1)
0;
0'
1<
0:
1H
b1 +
0F
1"
1#
#89000000
0#
#89500000
1E
06
04
0*
02
b1 .
07
05
03
b0 !
b0 ,
b0 /
01
1-
0@
1(
0?
0)
1C
0<
1A
0H
b10 +
1G
0"
1#
#90000000
0-
0#
#90500000
12
b11 .
0A
1B
b1 !
b1 ,
b1 /
11
0G
b100 +
1F
1-
1#
#91000000
0-
0#
#91500000
02
b1 .
13
b10 !
b10 ,
b10 /
01
1-
1#
#92000000
0-
0#
#92500000
14
12
b111 .
b11 !
b11 ,
b11 /
11
1-
1#
#93000000
0-
0#
#93500000
06
04
02
b1 .
15
03
b100 !
b100 ,
b100 /
01
1-
1#
#94000000
0-
0#
#94500000
12
b11 .
b101 !
b101 ,
b101 /
11
1-
1#
#95000000
0-
0#
#95500000
02
b1 .
13
b110 !
b110 ,
b110 /
01
1-
1#
#96000000
0-
0#
#96500000
16
14
12
b1111 .
b111 !
b111 ,
b111 /
11
1-
1#
#97000000
0-
0#
#97500000
06
04
02
b1 .
17
05
03
b1000 !
b1000 ,
b1000 /
01
1-
1#
#98000000
0-
0#
#98500000
12
b11 .
b1001 !
b1001 ,
b1001 /
11
1-
1#
#99000000
0-
0#
#99500000
02
b1 .
13
b1010 !
b1010 ,
b1010 /
01
1-
1#
#100000000
0-
0#
#100500000
14
12
b111 .
b1011 !
b1011 ,
b1011 /
11
1-
1#
#101000000
0-
0#
#101500000
06
04
02
b1 .
15
03
b1100 !
b1100 ,
b1100 /
01
1-
1#
#102000000
0-
0#
#102500000
12
b11 .
b1101 !
b1101 ,
b1101 /
11
1-
1#
#103000000
0-
0#
#103500000
02
b1 .
13
b1110 !
b1110 ,
b1110 /
01
1-
1#
#104000000
0-
0#
#104500000
0(
0C
0B
1;
16
1'
0E
1:
1*
14
12
b1111 .
b1111 !
b1111 ,
b1111 /
11
0-
1#
