Lab3/Serial_Adder_4bit.v
`timescale 1s / 1ns
module ShiftReg(in, en, clock, q);
  parameter n = 4;
  input in, en, clock;
  output[n-1:0] q;
  reg [n-1:0]q;
  initial
    q = 4'd10;
  always @ (posedge clock)
    begin
      if(en)
        q = {in, q[n-1:1]};
    end
endmodule

module DFlipFlop_Async_Clear(d, not_clear, clock, q);
  input d, not_clear, clock;
  output  q;
  reg q;
  always @ (negedge not_clear or posedge clock)
    begin
      if(!not_clear)
        q <= 1'b0;
      else
        q <= d;
    end
endmodule

module FADDER_1bit (Cout, Sum, In1, In2, Cin);
    input In1, In2, Cin;
    output Cout;
    output Sum;
    assign {Cout,Sum} = In1+In2+Cin;
endmodule

module Serial_Adder_4bit(SO1, sum, SI, shiftCtrl, clear, clock);
    initial
    begin
      $dumpfile("Serial_Adder_4bit.vcd");
      $dumpvars;
    end

    output[3:0] SO1;
    output sum;
    input SI, shiftCtrl, clear, clock;

    wire cout, q, sum;
    wire[3:0] SO1, SO2;

    ShiftReg SR1(sum, shiftCtrl, clock, SO1);
    ShiftReg SR2(SI, shiftCtrl, clock, SO2);

    FADDER_1bit FA(cout, sum, SO1[0], SO2[0], q);
    DFlipFlop_Async_Clear DFF(cout, clear, clock & shiftCtrl, q);

endmodule

module tb_Serial_Adder;
    reg SI, shiftCtrl, clear, clock;
    wire[3:0] a;
    wire sum;

    reg[0:3] b;

    integer i;

    Serial_Adder_4bit SA(a, sum, SI, shiftCtrl, clear, clock);

    always @(posedge clock)
        $display($time, " ShftCtrl = %b ", shiftCtrl, " SI = %b ", SI," sum:= ",sum ," Acc = %b ", a, "Clk: = ",clock," dff_out = %b ", SA.DFF.q);

    initial
        begin
          shiftCtrl = 1'b1;
          clock = 1'b0;
          clear = 1'b0;
          #2 clear = 1'b1;
          
        //   a = 4'b0111;
          b = 4'b0110;

          for(i = 0; i < 4; i++)
          begin
            SI = b[i];
            #2 clock = 1'b1;
            #2 clock = 1'b0;
          end
        end

endmodule

Lab3/Serial_Adder_4bit.vcd
$date
	Fri Nov  1 21:01:43 2019
$end
$version
	Icarus Verilog
$end
$timescale
	1ns
$end
$scope module tb_Serial_Adder $end
$var wire 1 ! sum $end
$var wire 4 " a [3:0] $end
$var reg 1 # SI $end
$var reg 4 $ b [0:3] $end
$var reg 1 % clear $end
$var reg 1 & clock $end
$var reg 1 ' shiftCtrl $end
$var integer 32 ( i [31:0] $end
$scope module SA $end
$var wire 1 # SI $end
$var wire 1 % clear $end
$var wire 1 & clock $end
$var wire 1 ' shiftCtrl $end
$var wire 1 ! sum $end
$var wire 1 ) q $end
$var wire 1 * cout $end
$var wire 4 + SO2 [3:0] $end
$var wire 4 , SO1 [3:0] $end
$scope module DFF $end
$var wire 1 - clock $end
$var wire 1 % not_clear $end
$var wire 1 * d $end
$var reg 1 ) q $end
$upscope $end
$scope module FA $end
$var wire 1 ) Cin $end
$var wire 1 . In1 $end
$var wire 1 / In2 $end
$var wire 1 ! Sum $end
$var wire 1 * Cout $end
$upscope $end
$scope module SR1 $end
$var wire 1 & clock $end
$var wire 1 ' en $end
$var wire 1 ! in $end
$var reg 4 0 q [3:0] $end
$upscope $end
$scope module SR2 $end
$var wire 1 & clock $end
$var wire 1 ' en $end
$var wire 1 # in $end
$var reg 4 1 q [3:0] $end
$upscope $end
$upscope $end
$upscope $end
$enddefinitions $end
#0
$dumpvars
b1010 1
b1010 0
0/
0.
0-
b1010 ,
b1010 +
0*
0)
bx (
1'
0&
0%
bx $
x#
b1010 "
0!
$end
#2000000000
0#
b0 (
b110 $
1%
#4000000000
1*
1.
1/
1-
b101 "
b101 ,
b101 0
b101 +
b101 1
1&
#6000000000
0-
1#
b1 (
0&
#8000000000
1!
1)
0*
0/
0.
1-
b1010 +
b1010 1
b10 "
b10 ,
b10 0
1&
#10000000000
0-
b10 (
0&
#12000000000
0!
0)
1*
1.
1/
1-
b1001 "
b1001 ,
b1001 0
b1101 +
b1101 1
1&
#14000000000
0-
0#
b11 (
0&
#16000000000
1!
1)
0*
0/
0.
1-
b110 +
b110 1
b100 "
b100 ,
b100 0
1&
#18000000000
0-
b100 (
0&
