Lab3/SynchCounterJK.v
`timescale 1ns / 1ps
module JKFlipFlop(J, K, clock, Q);
  initial
    begin
      $dumpfile("SynchCounterJK.vcd");
      $dumpvars;
    end
  input J, K, clock;
  output Q;
  reg Q;
  initial
    Q = 1'b0;
  always @(posedge clock)
    case({J, K})
      2'b00:  Q <= Q;
      2'b01:  Q <= 1'b0;
      2'b10:  Q <= 1'b1;
      2'b11:  Q <= ~Q;
    endcase
endmodule

module SynchCounterJK(clk, Q);
    input clk;
    output[3:0] Q;
    wire w0, w1;
    
    assign w0 = Q[0] & Q[1];
    assign w1 = w0 & Q[2]; 

    JKFlipFlop F0(1'b1, 1'b1, clk, Q[0]);
    JKFlipFlop F1(Q[0], Q[0], clk, Q[1]);
    JKFlipFlop F2(w0, w0, clk, Q[2]);
    JKFlipFlop F3(w1, w1, clk, Q[3]);
endmodule

module SynchCounterJK_TB;
    reg clock;
    wire [3:0] Q;

    SynchCounterJK SCJK(clock, Q);

    // initial
    // begin
    //   clock = 1'b0;
    //   repeat (10)
    //   #2  clock = ~clock;
    // end

    initial 
        clock = 1'b0;
    
    always
        #2 clock = ~clock;

    initial
        begin
          $monitor($time, "  CLK = %b, Q = %b", clock, Q);
          #64 $finish;
        end
endmodule

Lab3/SynchCounterJK.vcd
$date
	Fri Nov  1 12:55:29 2019
$end
$version
	Icarus Verilog
$end
$timescale
	1ps
$end
$scope module SynchCounterJK_TB $end
$var wire 4 ! Q [3:0] $end
$var reg 1 " clock $end
$scope module SCJK $end
$var wire 1 " clk $end
$var wire 1 # w0 $end
$var wire 1 $ w1 $end
$var wire 4 % Q [3:0] $end
$scope module F0 $end
$var wire 1 & J $end
$var wire 1 ' K $end
$var wire 1 " clock $end
$var reg 1 ( Q $end
$upscope $end
$scope module F1 $end
$var wire 1 ) J $end
$var wire 1 * K $end
$var wire 1 " clock $end
$var reg 1 + Q $end
$upscope $end
$scope module F2 $end
$var wire 1 # J $end
$var wire 1 # K $end
$var wire 1 " clock $end
$var reg 1 , Q $end
$upscope $end
$scope module F3 $end
$var wire 1 $ J $end
$var wire 1 $ K $end
$var wire 1 " clock $end
$var reg 1 - Q $end
$upscope $end
$upscope $end
$upscope $end
$scope module SynchCounterJK_TB $end
$scope module SCJK $end
$scope module F0 $end
$upscope $end
$scope module F1 $end
$upscope $end
$scope module F2 $end
$upscope $end
$scope module F3 $end
$upscope $end
$upscope $end
$upscope $end
$scope module SynchCounterJK_TB $end
$scope module SCJK $end
$scope module F0 $end
$upscope $end
$scope module F1 $end
$upscope $end
$scope module F2 $end
$upscope $end
$scope module F3 $end
$upscope $end
$upscope $end
$upscope $end
$scope module SynchCounterJK_TB $end
$scope module SCJK $end
$scope module F0 $end
$upscope $end
$scope module F1 $end
$upscope $end
$scope module F2 $end
$upscope $end
$scope module F3 $end
$upscope $end
$upscope $end
$upscope $end
$enddefinitions $end
#0
$dumpvars
0-
0,
0+
0*
0)
0(
1'
1&
b0 %
0$
0#
0"
b0 !
$end
#2000
1*
1)
b1 !
b1 %
1(
1"
#4000
0"
#6000
0*
0)
1+
b10 !
b10 %
0(
1"
#8000
0"
#10000
1#
1*
1)
b11 !
b11 %
1(
1"
#12000
0"
#14000
0#
0*
0)
1,
0+
b100 !
b100 %
0(
1"
#16000
0"
#18000
1*
1)
b101 !
b101 %
1(
1"
#20000
0"
#22000
0*
0)
1+
b110 !
b110 %
0(
1"
#24000
0"
#26000
1$
1#
1*
1)
b111 !
b111 %
1(
1"
#28000
0"
#30000
0$
0#
0*
0)
1-
0,
0+
b1000 !
b1000 %
0(
1"
#32000
0"
#34000
1*
1)
b1001 !
b1001 %
1(
1"
#36000
0"
#38000
0*
0)
1+
b1010 !
b1010 %
0(
1"
#40000
0"
#42000
1#
1*
1)
b1011 !
b1011 %
1(
1"
#44000
0"
#46000
0#
0*
0)
1,
0+
b1100 !
b1100 %
0(
1"
#48000
0"
#50000
1*
1)
b1101 !
b1101 %
1(
1"
#52000
0"
#54000
0*
0)
1+
b1110 !
b1110 %
0(
1"
#56000
0"
#58000
1$
1#
1*
1)
b1111 !
b1111 %
1(
1"
#60000
0"
#62000
0$
0#
0*
0)
0-
0,
0+
b0 !
b0 %
0(
1"
